toolkits/__init__.py
toolkits/bottle.py
toolkits/cipher.py
toolkits/database.py
toolkits/files.py
toolkits/http.py
toolkits/mongo.py
toolkits/plots.py
toolkits/redis.py
toolkits/reports.py
toolkits/sendemail.py
toolkits/utils.py
toolkits/weixin.py
toolkits/xftp.py
toolkits/zabbix.py
ez_toolkits-2.15.1.dist-info/LICENSE
ez_toolkits-2.15.1.dist-info/METADATA
ez_toolkits-2.15.1.dist-info/WHEEL
ez_toolkits-2.15.1.dist-info/top_level.txt
ez_toolkits-2.15.1.dist-info/RECORD
