Metadata-Version: 2.1
Name: ez-toolkits
Version: 2.15.1
Summary: Easy Toolkits
Author: septvean
Author-email: septvean@gmail.com
Requires-Python: >=3.10
License-File: LICENSE
Requires-Dist: loguru (>=0.7.0)
